{"query":{"count":1,"created":"2017-04-17T16:21:35Z","lang":"en-US","results":{"channel":{"units":{"distance":"mi","pressure":"in","speed":"mph","temperature":"F"},"title":"Yahoo! Weather - Alcinopolis, MS, BR","link":"http://us.rd.yahoo.com/dailynews/rss/weather/Country__Country/*https://weather.yahoo.com/country/state/city-26804274/","description":"Yahoo! Weather for Alcinopolis, MS, BR","language":"en-us","lastBuildDate":"Mon, 17 Apr 2017 12:21 PM AMT","ttl":"60","location":{"city":"Alcinopolis","country":"Brazil","region":" MS"},"wind":{"chill":"87","direction":"180","speed":"6"},"atmosphere":{"humidity":"51","pressure":"1012.19","rising":"0","visibility":"10.0"},"astronomy":{"sunrise":"5:45 am","sunset":"5:23 pm"},"image":{"title":"Yahoo! Weather","width":"142","height":"18","link":"http://weather.yahoo.com","url":"http://l.yimg.com/a/i/brand/purplelogo//uh/us/news-wea.gif"},"item":{"title":"Conditions for Alcinopolis, MS, BR at 12:21 PM AMT","lat":"-18.215361","long":"-53.773579","link":"http://us.rd.yahoo.com/dailynews/rss/weather/Country__Country/*https://weather.yahoo.com/country/state/city-26804274/","pubDate":"Mon, 17 Apr 2017 12:21 PM AMT","condition":{"code":"30","date":"Mon, 17 Apr 2017 12:21 PM AMT","temp":"87","text":"Partly Cloudy"},"forecast":[{"code":"30","date":"17 Apr 2017","day":"Mon","high":"88","low":"69","text":"Partly Cloudy"},{"code":"38","date":"18 Apr 2017","day":"Tue","high":"90","low":"71","text":"Scattered Thundershowers"},{"code":"38","date":"19 Apr 2017","day":"Wed","high":"89","low":"71","text":"Scattered Thundershowers"},{"code":"4","date":"20 Apr 2017","day":"Thu","high":"84","low":"69","text":"Thunderstorms"},{"code":"4","date":"21 Apr 2017","day":"Fri","high":"78","low":"67","text":"Thunderstorms"},{"code":"30","date":"22 Apr 2017","day":"Sat","high":"82","low":"65","text":"Partly Cloudy"},{"code":"30","date":"23 Apr 2017","day":"Sun","high":"85","low":"67","text":"Partly Cloudy"},{"code":"34","date":"24 Apr 2017","day":"Mon","high":"87","low":"69","text":"Mostly Sunny"},{"code":"37","date":"25 Apr 2017","day":"Tue","high":"88","low":"70","text":"Isolated Thunderstorms"},{"code":"37","date":"26 Apr 2017","day":"Wed","high":"88","low":"71","text":"Isolated Thunderstorms"}],"description":"<![CDATA[<img src=\"http://l.yimg.com/a/i/us/we/52/30.gif\"/>\n<BR />\n<b>Current Conditions:</b>\n<BR />Partly Cloudy\n<BR />\n<BR />\n<b>Forecast:</b>\n<BR /> Mon - Partly Cloudy. High: 88Low: 69\n<BR /> Tue - Scattered Thundershowers. High: 90Low: 71\n<BR /> Wed - Scattered Thundershowers. High: 89Low: 71\n<BR /> Thu - Thunderstorms. High: 84Low: 69\n<BR /> Fri - Thunderstorms. High: 78Low: 67\n<BR />\n<BR />\n<a href=\"http://us.rd.yahoo.com/dailynews/rss/weather/Country__Country/*https://weather.yahoo.com/country/state/city-26804274/\">Full Forecast at Yahoo! Weather</a>\n<BR />\n<BR />\n(provided by <a href=\"http://www.weather.com\" >The Weather Channel</a>)\n<BR />\n]]>","guid":{"isPermaLink":"false"}}}}}}