{"query":{"count":1,"created":"2017-04-17T17:01:29Z","lang":"en-US","results":{"channel":{"units":{"distance":"mi","pressure":"in","speed":"mph","temperature":"F"},"title":"Yahoo! Weather - Casimiro de Abreu, RJ, BR","link":"http://us.rd.yahoo.com/dailynews/rss/weather/Country__Country/*https://weather.yahoo.com/country/state/city-428859/","description":"Yahoo! Weather for Casimiro de Abreu, RJ, BR","language":"en-us","lastBuildDate":"Mon, 17 Apr 2017 02:01 PM BRT","ttl":"60","location":{"city":"Casimiro de Abreu","country":"Brazil","region":" RJ"},"wind":{"chill":"84","direction":"225","speed":"18"},"atmosphere":{"humidity":"55","pressure":"1006.0","rising":"0","visibility":"16.1"},"astronomy":{"sunrise":"6:1 am","sunset":"5:33 pm"},"image":{"title":"Yahoo! Weather","width":"142","height":"18","link":"http://weather.yahoo.com","url":"http://l.yimg.com/a/i/brand/purplelogo//uh/us/news-wea.gif"},"item":{"title":"Conditions for Casimiro de Abreu, RJ, BR at 01:00 PM BRT","lat":"-22.499109","long":"-42.273201","link":"http://us.rd.yahoo.com/dailynews/rss/weather/Country__Country/*https://weather.yahoo.com/country/state/city-428859/","pubDate":"Mon, 17 Apr 2017 01:00 PM BRT","condition":{"code":"30","date":"Mon, 17 Apr 2017 01:00 PM BRT","temp":"85","text":"Partly Cloudy"},"forecast":[{"code":"30","date":"17 Apr 2017","day":"Mon","high":"87","low":"67","text":"Partly Cloudy"},{"code":"12","date":"18 Apr 2017","day":"Tue","high":"76","low":"68","text":"Rain"},{"code":"28","date":"19 Apr 2017","day":"Wed","high":"75","low":"66","text":"Mostly Cloudy"},{"code":"28","date":"20 Apr 2017","day":"Thu","high":"79","low":"64","text":"Mostly Cloudy"},{"code":"28","date":"21 Apr 2017","day":"Fri","high":"87","low":"60","text":"Mostly Cloudy"},{"code":"30","date":"22 Apr 2017","day":"Sat","high":"90","low":"65","text":"Partly Cloudy"},{"code":"28","date":"23 Apr 2017","day":"Sun","high":"83","low":"69","text":"Mostly Cloudy"},{"code":"28","date":"24 Apr 2017","day":"Mon","high":"77","low":"71","text":"Mostly Cloudy"},{"code":"30","date":"25 Apr 2017","day":"Tue","high":"78","low":"69","text":"Partly Cloudy"},{"code":"4","date":"26 Apr 2017","day":"Wed","high":"83","low":"68","text":"Thunderstorms"}],"description":"<![CDATA[<img src=\"http://l.yimg.com/a/i/us/we/52/30.gif\"/>\n<BR />\n<b>Current Conditions:</b>\n<BR />Partly Cloudy\n<BR />\n<BR />\n<b>Forecast:</b>\n<BR /> Mon - Partly Cloudy. High: 87Low: 67\n<BR /> Tue - Rain. High: 76Low: 68\n<BR /> Wed - Mostly Cloudy. High: 75Low: 66\n<BR /> Thu - Mostly Cloudy. High: 79Low: 64\n<BR /> Fri - Mostly Cloudy. High: 87Low: 60\n<BR />\n<BR />\n<a href=\"http://us.rd.yahoo.com/dailynews/rss/weather/Country__Country/*https://weather.yahoo.com/country/state/city-428859/\">Full Forecast at Yahoo! Weather</a>\n<BR />\n<BR />\n(provided by <a href=\"http://www.weather.com\" >The Weather Channel</a>)\n<BR />\n]]>","guid":{"isPermaLink":"false"}}}}}}