{"query":{"count":1,"created":"2017-04-17T17:31:07Z","lang":"en-US","results":{"channel":{"units":{"distance":"mi","pressure":"in","speed":"mph","temperature":"F"},"title":"Yahoo! Weather - Irineopolis, SC, BR","link":"http://us.rd.yahoo.com/dailynews/rss/weather/Country__Country/*https://weather.yahoo.com/country/state/city-12581682/","description":"Yahoo! Weather for Irineopolis, SC, BR","language":"en-us","lastBuildDate":"Mon, 17 Apr 2017 02:31 PM BRT","ttl":"60","location":{"city":"Irineopolis","country":"Brazil","region":" SC"},"wind":{"chill":"63","direction":"113","speed":"11"},"atmosphere":{"humidity":"85","pressure":"924.0","rising":"0","visibility":"16.1"},"astronomy":{"sunrise":"6:40 am","sunset":"6:6 pm"},"image":{"title":"Yahoo! Weather","width":"142","height":"18","link":"http://weather.yahoo.com","url":"http://l.yimg.com/a/i/brand/purplelogo//uh/us/news-wea.gif"},"item":{"title":"Conditions for Irineopolis, SC, BR at 02:00 PM BRT","lat":"-26.35581","long":"-50.768311","link":"http://us.rd.yahoo.com/dailynews/rss/weather/Country__Country/*https://weather.yahoo.com/country/state/city-12581682/","pubDate":"Mon, 17 Apr 2017 02:00 PM BRT","condition":{"code":"26","date":"Mon, 17 Apr 2017 02:00 PM BRT","temp":"63","text":"Cloudy"},"forecast":[{"code":"26","date":"17 Apr 2017","day":"Mon","high":"64","low":"60","text":"Cloudy"},{"code":"26","date":"18 Apr 2017","day":"Tue","high":"67","low":"58","text":"Cloudy"},{"code":"26","date":"19 Apr 2017","day":"Wed","high":"67","low":"58","text":"Cloudy"},{"code":"28","date":"20 Apr 2017","day":"Thu","high":"69","low":"52","text":"Mostly Cloudy"},{"code":"47","date":"21 Apr 2017","day":"Fri","high":"71","low":"60","text":"Scattered Thunderstorms"},{"code":"47","date":"22 Apr 2017","day":"Sat","high":"67","low":"60","text":"Scattered Thunderstorms"},{"code":"12","date":"23 Apr 2017","day":"Sun","high":"70","low":"60","text":"Rain"},{"code":"28","date":"24 Apr 2017","day":"Mon","high":"70","low":"60","text":"Mostly Cloudy"},{"code":"30","date":"25 Apr 2017","day":"Tue","high":"74","low":"59","text":"Partly Cloudy"},{"code":"30","date":"26 Apr 2017","day":"Wed","high":"71","low":"59","text":"Partly Cloudy"}],"description":"<![CDATA[<img src=\"http://l.yimg.com/a/i/us/we/52/26.gif\"/>\n<BR />\n<b>Current Conditions:</b>\n<BR />Cloudy\n<BR />\n<BR />\n<b>Forecast:</b>\n<BR /> Mon - Cloudy. High: 64Low: 60\n<BR /> Tue - Cloudy. High: 67Low: 58\n<BR /> Wed - Cloudy. High: 67Low: 58\n<BR /> Thu - Mostly Cloudy. High: 69Low: 52\n<BR /> Fri - Scattered Thunderstorms. High: 71Low: 60\n<BR />\n<BR />\n<a href=\"http://us.rd.yahoo.com/dailynews/rss/weather/Country__Country/*https://weather.yahoo.com/country/state/city-12581682/\">Full Forecast at Yahoo! Weather</a>\n<BR />\n<BR />\n(provided by <a href=\"http://www.weather.com\" >The Weather Channel</a>)\n<BR />\n]]>","guid":{"isPermaLink":"false"}}}}}}