{"query":{"count":1,"created":"2017-04-17T16:58:41Z","lang":"en-US","results":{"channel":{"units":{"distance":"mi","pressure":"in","speed":"mph","temperature":"F"},"title":"Yahoo! Weather - Santa Isabel Do Ivai, PR, BR","link":"http://us.rd.yahoo.com/dailynews/rss/weather/Country__Country/*https://weather.yahoo.com/country/state/city-460909/","description":"Yahoo! Weather for Santa Isabel Do Ivai, PR, BR","language":"en-us","lastBuildDate":"Mon, 17 Apr 2017 01:58 PM BRT","ttl":"60","location":{"city":"Santa Isabel Do Ivai","country":"Brazil","region":" PR"},"wind":{"chill":"79","direction":"135","speed":"7"},"atmosphere":{"humidity":"65","pressure":"971.0","rising":"0","visibility":"16.1"},"astronomy":{"sunrise":"6:47 am","sunset":"6:18 pm"},"image":{"title":"Yahoo! Weather","width":"142","height":"18","link":"http://weather.yahoo.com","url":"http://l.yimg.com/a/i/brand/purplelogo//uh/us/news-wea.gif"},"item":{"title":"Conditions for Santa Isabel Do Ivai, PR, BR at 01:00 PM BRT","lat":"-23.002899","long":"-53.199219","link":"http://us.rd.yahoo.com/dailynews/rss/weather/Country__Country/*https://weather.yahoo.com/country/state/city-460909/","pubDate":"Mon, 17 Apr 2017 01:00 PM BRT","condition":{"code":"28","date":"Mon, 17 Apr 2017 01:00 PM BRT","temp":"79","text":"Mostly Cloudy"},"forecast":[{"code":"30","date":"17 Apr 2017","day":"Mon","high":"81","low":"65","text":"Partly Cloudy"},{"code":"26","date":"18 Apr 2017","day":"Tue","high":"80","low":"68","text":"Cloudy"},{"code":"26","date":"19 Apr 2017","day":"Wed","high":"82","low":"67","text":"Cloudy"},{"code":"39","date":"20 Apr 2017","day":"Thu","high":"76","low":"69","text":"Scattered Showers"},{"code":"47","date":"21 Apr 2017","day":"Fri","high":"72","low":"67","text":"Scattered Thunderstorms"},{"code":"28","date":"22 Apr 2017","day":"Sat","high":"76","low":"63","text":"Mostly Cloudy"},{"code":"30","date":"23 Apr 2017","day":"Sun","high":"78","low":"63","text":"Partly Cloudy"},{"code":"34","date":"24 Apr 2017","day":"Mon","high":"81","low":"65","text":"Mostly Sunny"},{"code":"30","date":"25 Apr 2017","day":"Tue","high":"83","low":"68","text":"Partly Cloudy"},{"code":"47","date":"26 Apr 2017","day":"Wed","high":"77","low":"69","text":"Scattered Thunderstorms"}],"description":"<![CDATA[<img src=\"http://l.yimg.com/a/i/us/we/52/28.gif\"/>\n<BR />\n<b>Current Conditions:</b>\n<BR />Mostly Cloudy\n<BR />\n<BR />\n<b>Forecast:</b>\n<BR /> Mon - Partly Cloudy. High: 81Low: 65\n<BR /> Tue - Cloudy. High: 80Low: 68\n<BR /> Wed - Cloudy. High: 82Low: 67\n<BR /> Thu - Scattered Showers. High: 76Low: 69\n<BR /> Fri - Scattered Thunderstorms. High: 72Low: 67\n<BR />\n<BR />\n<a href=\"http://us.rd.yahoo.com/dailynews/rss/weather/Country__Country/*https://weather.yahoo.com/country/state/city-460909/\">Full Forecast at Yahoo! Weather</a>\n<BR />\n<BR />\n(provided by <a href=\"http://www.weather.com\" >The Weather Channel</a>)\n<BR />\n]]>","guid":{"isPermaLink":"false"}}}}}}