{"query":{"count":1,"created":"2017-04-17T17:24:38Z","lang":"en-US","results":{"channel":{"units":{"distance":"mi","pressure":"in","speed":"mph","temperature":"F"},"title":"Yahoo! Weather - Santo Expedito do Sul, RS, BR","link":"http://us.rd.yahoo.com/dailynews/rss/weather/Country__Country/*https://weather.yahoo.com/country/state/city-26804257/","description":"Yahoo! Weather for Santo Expedito do Sul, RS, BR","language":"en-us","lastBuildDate":"Mon, 17 Apr 2017 02:24 PM BRT","ttl":"60","location":{"city":"Santo Expedito do Sul","country":"Brazil","region":" RS"},"wind":{"chill":"68","direction":"90","speed":"14"},"atmosphere":{"humidity":"71","pressure":"933.0","rising":"0","visibility":"16.1"},"astronomy":{"sunrise":"6:44 am","sunset":"6:7 pm"},"image":{"title":"Yahoo! Weather","width":"142","height":"18","link":"http://weather.yahoo.com","url":"http://l.yimg.com/a/i/brand/purplelogo//uh/us/news-wea.gif"},"item":{"title":"Conditions for Santo Expedito do Sul, RS, BR at 01:00 PM BRT","lat":"-27.90391","long":"-51.65799","link":"http://us.rd.yahoo.com/dailynews/rss/weather/Country__Country/*https://weather.yahoo.com/country/state/city-26804257/","pubDate":"Mon, 17 Apr 2017 01:00 PM BRT","condition":{"code":"28","date":"Mon, 17 Apr 2017 01:00 PM BRT","temp":"68","text":"Mostly Cloudy"},"forecast":[{"code":"30","date":"17 Apr 2017","day":"Mon","high":"69","low":"57","text":"Partly Cloudy"},{"code":"30","date":"18 Apr 2017","day":"Tue","high":"72","low":"58","text":"Partly Cloudy"},{"code":"26","date":"19 Apr 2017","day":"Wed","high":"72","low":"58","text":"Cloudy"},{"code":"26","date":"20 Apr 2017","day":"Thu","high":"72","low":"58","text":"Cloudy"},{"code":"26","date":"21 Apr 2017","day":"Fri","high":"70","low":"64","text":"Cloudy"},{"code":"12","date":"22 Apr 2017","day":"Sat","high":"68","low":"60","text":"Rain"},{"code":"30","date":"23 Apr 2017","day":"Sun","high":"71","low":"59","text":"Partly Cloudy"},{"code":"30","date":"24 Apr 2017","day":"Mon","high":"71","low":"60","text":"Partly Cloudy"},{"code":"30","date":"25 Apr 2017","day":"Tue","high":"73","low":"61","text":"Partly Cloudy"},{"code":"30","date":"26 Apr 2017","day":"Wed","high":"69","low":"55","text":"Partly Cloudy"}],"description":"<![CDATA[<img src=\"http://l.yimg.com/a/i/us/we/52/28.gif\"/>\n<BR />\n<b>Current Conditions:</b>\n<BR />Mostly Cloudy\n<BR />\n<BR />\n<b>Forecast:</b>\n<BR /> Mon - Partly Cloudy. High: 69Low: 57\n<BR /> Tue - Partly Cloudy. High: 72Low: 58\n<BR /> Wed - Cloudy. High: 72Low: 58\n<BR /> Thu - Cloudy. High: 72Low: 58\n<BR /> Fri - Cloudy. High: 70Low: 64\n<BR />\n<BR />\n<a href=\"http://us.rd.yahoo.com/dailynews/rss/weather/Country__Country/*https://weather.yahoo.com/country/state/city-26804257/\">Full Forecast at Yahoo! Weather</a>\n<BR />\n<BR />\n(provided by <a href=\"http://www.weather.com\" >The Weather Channel</a>)\n<BR />\n]]>","guid":{"isPermaLink":"false"}}}}}}